watchmen_storage_s3/__init__.py
watchmen_storage_s3/data_source_s3.py
watchmen_storage_s3/object_defs_s3.py
watchmen_storage_s3/simple_storage_service.py
watchmen_storage_s3/storage_s3.py
watchmen_storage_s3/storage_s3_configuration.py
watchmen_storage_s3/where_build.py
watchmen_storage_s3-18.0.1.dist-info/METADATA
watchmen_storage_s3-18.0.1.dist-info/WHEEL
watchmen_storage_s3-18.0.1.dist-info/licenses/LICENSE
watchmen_storage_s3-18.0.1.dist-info/RECORD
